gdpx/config.py
gdpx/main.py
gdpx/bias/__init__.py
gdpx/bias/bias.py
gdpx/bias/bondboost.py
gdpx/bias/nuclei.py
gdpx/bias/timeio.py
gdpx/bias/afir/__init__.py
gdpx/bias/afir/afir.py
gdpx/bias/gaussian/__init__.py
gdpx/bias/gaussian/bond.py
gdpx/bias/gaussian/com.py
gdpx/bias/gaussian/distance.py
gdpx/bias/gaussian/gaussian.py
gdpx/bias/gaussian/rmsd.py
gdpx/bias/harmonic/__init__.py
gdpx/bias/harmonic/distance.py
gdpx/bias/harmonic/harmonic.py
gdpx/bias/harmonic/plane.py
gdpx/bias/utils/__init__.py
gdpx/bias/utils/bondpair.py
gdpx/builder/__init__.py
gdpx/builder/builder.py
gdpx/builder/cleave_group.py
gdpx/builder/cleave_surface.py
gdpx/builder/constraints.py
gdpx/builder/crossover.py
gdpx/builder/dimer.py
gdpx/builder/direct.py
gdpx/builder/group.py
gdpx/builder/insert.py
gdpx/builder/interface.py
gdpx/builder/packer.py
gdpx/builder/perturbator.py
gdpx/builder/randomBuilder.py
gdpx/builder/region.py
gdpx/builder/repeat.py
gdpx/builder/species.py
gdpx/builder/utils.py
gdpx/builder/wulff.py
gdpx/builder/zoom.py
gdpx/builder/graph/__init__.py
gdpx/builder/graph/exchange.py
gdpx/builder/graph/insert.py
gdpx/builder/graph/modifier.py
gdpx/builder/graph/remove.py
gdpx/builder/mutation/__init__.py
gdpx/builder/scan/angle.py
gdpx/builder/scan/hypercube.py
gdpx/builder/scan/intercoord.py
gdpx/cli/build.py
gdpx/cli/compute.py
gdpx/cli/explore.py
gdpx/cli/select.py
gdpx/colvar/__init__.py
gdpx/colvar/coordination.py
gdpx/colvar/distance.py
gdpx/colvar/fingerprint.py
gdpx/colvar/position.py
gdpx/colvar/rmsd.py
gdpx/comparator/__init__.py
gdpx/comparator/cartesian.py
gdpx/comparator/comparator.py
gdpx/comparator/coordination.py
gdpx/comparator/graph.py
gdpx/comparator/interface.py
gdpx/comparator/reaction.py
gdpx/comparator/singlepoint.py
gdpx/computation/__init__.py
gdpx/computation/abacus.py
gdpx/computation/asedriver.py
gdpx/computation/cp2k.py
gdpx/computation/driver.py
gdpx/computation/espresso.py
gdpx/computation/interface.py
gdpx/computation/lammps.py
gdpx-0.0.10.dist-info/LICENSE
gdpx-0.0.10.dist-info/METADATA
gdpx-0.0.10.dist-info/WHEEL
gdpx-0.0.10.dist-info/entry_points.txt
gdpx-0.0.10.dist-info/top_level.txt
gdpx-0.0.10.dist-info/RECORD
