Metadata-Version: 2.1
Name: gdpx
Version: 0.0.10
Summary: Automate computational chemistry/materials sciance and machine learning interatomic potential training workflow.
Author-email: Jiayan Xu <ahcigar@foxmail.com>
License: GNU GENERAL PUBLIC LICENSE
Project-URL: Homepage, https://github.com/hsulab/GDPy
Project-URL: Issues, https://github.com/hsulab/GDPy/issues
Classifier: Programming Language :: Python :: 3
Classifier: License :: OSI Approved :: GNU General Public License v3 (GPLv3)
Classifier: Operating System :: OS Independent
Requires-Python: >=3.9
License-File: LICENSE
Requires-Dist: ase >=3.23
Requires-Dist: h5py >=3.7.0
Requires-Dist: joblib >=1.1.0
Requires-Dist: networkx >=2.6.3
Requires-Dist: omegaconf >=2.3.0
Requires-Dist: pyyaml >=6.0
Requires-Dist: tinydb >=4.7.0
